README.md
setup.py
datastories/__init__.py
datastories/analytical.py
datastories.egg-info/PKG-INFO
datastories.egg-info/SOURCES.txt
datastories.egg-info/dependency_links.txt
datastories.egg-info/not-zip-safe
datastories.egg-info/requires.txt
datastories.egg-info/top_level.txt