Metadata-Version: 2.1
Name: datastories
Version: 0.3.11
Summary: Data Story Pattern Analysis for LOSD
Home-page: https://github.com/MaciejJanowski/DataStoryPatternLibrary
Author: Maciej Janowski
Author-email: maciej.janowski@insight-centre.org
License: MIT
Platform: UNKNOWN
